CHANGELOG.rst
Dockerfile
LICENSE
MANIFEST.in
README.rst
docker-compose.yml
edwiges.ini
requirements.txt
setup.py
edwiges/__init__.py
edwiges/schema.py
edwiges/util.py
edwiges/views.py
edwiges.egg-info/PKG-INFO
edwiges.egg-info/SOURCES.txt
edwiges.egg-info/dependency_links.txt
edwiges.egg-info/entry_points.txt
edwiges.egg-info/not-zip-safe
edwiges.egg-info/requires.txt
edwiges.egg-info/top_level.txt