Metadata-Version: 1.1
Name: edwiges
Version: 0.1.0
Summary: A stupidly simple email REST service.
Home-page: https://github.com/loggi/edwiges
Author: Gabriela Surita
Author-email: gsurita@loggi.com
License: Apache Licence v2.0
Keywords: web services
Platform: UNKNOWN
Classifier: Programming Language :: Python
Classifier: Programming Language :: Python :: 2
Classifier: Programming Language :: Python :: 2.7
Classifier: Programming Language :: Python :: 3
Classifier: Programming Language :: Python :: 3.4
Classifier: Programming Language :: Python :: 3.5
Classifier: Programming Language :: Python :: 3.6
Classifier: Framework :: Pylons
Classifier: Topic :: Internet :: WWW/HTTP
Classifier: Topic :: Internet :: WWW/HTTP :: WSGI :: Application
